syndot/__init__.py
syndot/__main__.py
syndot/init_config.py
syndot/version.py
syndot/_colorschemes/Catppuccin.colorscheme
syndot/_colorschemes/default.colorscheme
syndot/_templates/map.ini
syndot/_templates/style.ini
syndot/commands/__init__.py
syndot/commands/add.py
syndot/commands/diffuse.py
syndot/commands/init.py
syndot/commands/link.py
syndot/commands/list_.py
syndot/commands/remove.py
syndot/commands/rename.py
syndot/commands/unlink.py
syndot/parser/__init__.py
syndot/parser/add_parser.py
syndot/parser/diffuse_parser.py
syndot/parser/init_parser.py
syndot/parser/link_parser.py
syndot/parser/list_parser.py
syndot/parser/parser.py
syndot/parser/remove_parser.py
syndot/parser/rename_parser.py
syndot/parser/unlink_parser.py
syndot/utils/__init__.py
syndot/utils/colors.py
syndot/utils/commands.py
syndot/utils/file_actions.py
syndot/utils/gum_style.py
syndot/utils/logger.py
syndot/utils/map_file.py
syndot/utils/path.py
syndot/utils/print_.py
syndot/utils/prompt.py
syndot/utils/system_info.py
syndot-2.3.0.dist-info/licenses/LICENSE
syndot-2.3.0.dist-info/METADATA
syndot-2.3.0.dist-info/WHEEL
syndot-2.3.0.dist-info/top_level.txt
syndot-2.3.0.dist-info/RECORD
