Metadata-Version: 2.4
Name: syndot
Version: 2.3.0
Summary: Dotfiles link management tool
Author-email: Andrea Blengino <ing.andrea.blengino@protonmail.com>
Maintainer-email: Andrea Blengino <ing.andrea.blengino@protonmail.com>
License:                     GNU GENERAL PUBLIC LICENSE
Project-URL: Homepage, https://github.com/AndreaBlengino/syndot
Project-URL: Documentation, https://syndot.readthedocs.io/en/latest/index.html
Project-URL: Issues, https://github.com/AndreaBlengino/syndot/issues
Project-URL: Repository, https://github.com/AndreaBlengino/syndot
Classifier: Development Status :: 5 - Production/Stable
Classifier: Environment :: Console
Classifier: Intended Audience :: End Users/Desktop
Classifier: Operating System :: POSIX :: Linux
Classifier: Operating System :: MacOS
Classifier: Programming Language :: Python
Classifier: Programming Language :: Python :: 3.11
Classifier: Programming Language :: Python :: 3.12
Classifier: Programming Language :: Python :: 3.13
Classifier: Programming Language :: Python :: 3.14
Classifier: Topic :: Desktop Environment :: File Managers
Requires-Python: >=3.11
License-File: LICENSE
Provides-Extra: doc
Requires-Dist: furo==2024.8.6; extra == "doc"
Requires-Dist: sphinx==8.1.3; extra == "doc"
Requires-Dist: sphinx-copybutton==0.5.2; extra == "doc"
Provides-Extra: test
Requires-Dist: coverage==7.6.3; extra == "test"
Requires-Dist: hypothesis==6.108.5; extra == "test"
Requires-Dist: pytest==8.3.3; extra == "test"
Requires-Dist: pytest-cov==5.0.0; extra == "test"
Dynamic: license-file
